yoctopuce/__init__.py
yoctopuce/yocto_accelerometer.py
yoctopuce/yocto_altitude.py
yoctopuce/yocto_anbutton.py
yoctopuce/yocto_angularspeed.py
yoctopuce/yocto_api.py
yoctopuce/yocto_arithmeticsensor.py
yoctopuce/yocto_audioin.py
yoctopuce/yocto_audioout.py
yoctopuce/yocto_bluetoothlink.py
yoctopuce/yocto_buzzer.py
yoctopuce/yocto_carbondioxide.py
yoctopuce/yocto_cellular.py
yoctopuce/yocto_colorled.py
yoctopuce/yocto_colorledcluster.py
yoctopuce/yocto_colorsensor.py
yoctopuce/yocto_compass.py
yoctopuce/yocto_counter.py
yoctopuce/yocto_current.py
yoctopuce/yocto_currentloopoutput.py
yoctopuce/yocto_daisychain.py
yoctopuce/yocto_datalogger.py
yoctopuce/yocto_digitalio.py
yoctopuce/yocto_display.py
yoctopuce/yocto_dualpower.py
yoctopuce/yocto_files.py
yoctopuce/yocto_genericsensor.py
yoctopuce/yocto_gps.py
yoctopuce/yocto_groundspeed.py
yoctopuce/yocto_gyro.py
yoctopuce/yocto_hubport.py
yoctopuce/yocto_humidity.py
yoctopuce/yocto_i2cport.py
yoctopuce/yocto_inputcapture.py
yoctopuce/yocto_inputchain.py
yoctopuce/yocto_latitude.py
yoctopuce/yocto_led.py
yoctopuce/yocto_lightsensor.py
yoctopuce/yocto_longitude.py
yoctopuce/yocto_magnetometer.py
yoctopuce/yocto_messagebox.py
yoctopuce/yocto_micropython.py
yoctopuce/yocto_motor.py
yoctopuce/yocto_multiaxiscontroller.py
yoctopuce/yocto_multicellweighscale.py
yoctopuce/yocto_multisenscontroller.py
yoctopuce/yocto_network.py
yoctopuce/yocto_orientation.py
yoctopuce/yocto_oscontrol.py
yoctopuce/yocto_power.py
yoctopuce/yocto_poweroutput.py
yoctopuce/yocto_powersupply.py
yoctopuce/yocto_pressure.py
yoctopuce/yocto_proximity.py
yoctopuce/yocto_pwminput.py
yoctopuce/yocto_pwmoutput.py
yoctopuce/yocto_pwmpowersource.py
yoctopuce/yocto_quadraturedecoder.py
yoctopuce/yocto_rangefinder.py
yoctopuce/yocto_realtimeclock.py
yoctopuce/yocto_refframe.py
yoctopuce/yocto_relay.py
yoctopuce/yocto_rfidreader.py
yoctopuce/yocto_sdi12port.py
yoctopuce/yocto_segmenteddisplay.py
yoctopuce/yocto_serialport.py
yoctopuce/yocto_servo.py
yoctopuce-2.1.11632.dist-info/METADATA
yoctopuce-2.1.11632.dist-info/WHEEL
yoctopuce-2.1.11632.dist-info/licenses/LICENSE.txt
yoctopuce-2.1.11632.dist-info/RECORD
